taxi_printing/__init__.py
taxi_printing/classes.py
taxi_printing/data_processor.py
taxi_printing/dollars_to_words.py
taxi_printing/google_sheets.py
taxi_printing/print_dockets.py
taxi_printing-0.0.8.dist-info/METADATA
taxi_printing-0.0.8.dist-info/WHEEL
taxi_printing-0.0.8.dist-info/licenses/LICENSE
taxi_printing-0.0.8.dist-info/RECORD
