Metadata-Version: 2.3
Name: taxi_printing
Version: 0.0.8
Summary: Mail merge and print dockets and lodgment envelope
Project-URL: Homepage, https://github.com/WayneBennett666/taxi-printing
Project-URL: Issues, https://github.com/WayneBennett666/taxi-printing/issues
Author-email: Wayne Bennett <wayne.bennett@live.com>
License-File: LICENSE
Classifier: License :: OSI Approved :: MIT License
Classifier: Operating System :: OS Independent
Classifier: Programming Language :: Python :: 3
Requires-Python: >=3.10
